{
  "total_passes": 10,
  "target_passes": 10,
  "passes": [
    {
      "pass_number": 1,
      "start_time": "2025-08-23T19:13:27.528117",
      "loops": [
        {
          "loop": "LOOP1",
          "script": "scripts/mission_loop1.py",
          "success": true,
          "duration": 0.015559673309326172,
          "output": "FEATURE_ACTIVITY_MAP.md already exists, enhancing...\n\u2713 Loop 1 complete\n"
        },
        {
          "loop": "LOOP2",
          "script": "scripts/mission_loop2.py",
          "success": true,
          "duration": 0.015038251876831055,
          "output": "Generating ENV_BUG_DATA_AUDIT.md...\nGenerating DATA_CYCLE_MAP.md...\n\u2713 Loop 2 complete\n"
        },
        {
          "loop": "LOOP3",
          "script": "scripts/mission_loop3.py",
          "success": true,
          "duration": 0.009066104888916016,
          "output": "Generating ARCH_DECISIONS.md...\nGenerating ARCH_BLUEPRINT.md...\n\u2713 Loop 3 complete\n"
        },
        {
          "loop": "LOOP4",
          "script": "scripts/mission_loop4.py",
          "success": true,
          "duration": 0.009641647338867188,
          "output": "Enhancing FEATURE_ACTIVITY_MAP.md with routes...\nUpdating legacy_vs_current_diff.md...\n\u2713 Loop 4 complete\n"
        },
        {
          "loop": "LOOP5",
          "script": "scripts/mission_loop5.py",
          "success": true,
          "duration": 0.01664113998413086,
          "output": "Building IMPLEMENTATION_CHECKLIST.md...\n\u2713 Loop 5 complete - 324 items created\n"
        },
        {
          "loop": "LOOP6",
          "script": "scripts/mission_loop6.py",
          "success": true,
          "duration": 0.15643715858459473,
          "output": "Loading all reports and data...\nCalculating alignment delta...\nBuilding crosslinks...\nGenerating source of truth document...\nGenerating organizer manifest...\n\n\u2713 Source of Truth document created: docs/plan/OPENPOLICY_V2_SOURCE_OF_TRUTH.md\n\u2713 Organizer manifest created: reports/organizer_manifest.json\n\nAlignment Summary:\n  - architecture: 50.0%\n  - features: 0.0%\n  - data_flow: 80.6%\n  - routing: 1.3%\n  - quality: 100.0%\n  - operations: 0.0%\nRunning organizer and updating Source of Truth...\nRunning source_of_truth.py...\n\u2713 Loop 6 complete\n"
        }
      ],
      "enhancement_cycles": {
        "loop": "ENHANCE",
        "script": "scripts/mission_enhance.py",
        "success": true,
        "duration": 0.0311892032623291,
        "output": "\nRunning enhancement cycle 1/10...\n  \u2713 Cycle 1 complete - all 324 items enhanced\n\nRunning enhancement cycle 2/10...\n  \u2713 Cycle 2 complete - all 324 items enhanced\n\nRunning enhancement cycle 3/10...\n  \u2713 Cycle 3 complete - all 324 items enhanced\n\nRunning enhancement cycle 4/10...\n  \u2713 Cycle 4 complete - all 324 items enhanced\n\nRunning enhancement cycle 5/10...\n  \u2713 Cycle 5 complete - all 324 items enhanced\n\nRunning enhancement cycle 6/10...\n  \u2713 Cycle 6 complete - all 324 items enhanced\n\nRunning enhancement cycle 7/10...\n  \u2713 Cycle 7 complete - all 324 items enhanced\n\nRunning enhancement cycle 8/10...\n  \u2713 Cycle 8 complete - all 324 items enhanced\n\nRunning enhancement cycle 9/10...\n  \u2713 Cycle 9 complete - all 324 items enhanced\n\nRunning enhancement cycle 10/10...\n  \u2713 Cycle 10 complete - all 324 items enhanced\n\n\u2713 All 10 enhancement cycles complete!\n"
      },
      "end_time": "2025-08-23T19:13:27.781765",
      "duration": 0.25365591049194336,
      "success": true
    },
    {
      "pass_number": 2,
      "start_time": "2025-08-23T19:13:27.782103",
      "loops": [
        {
          "loop": "LOOP1",
          "script": "scripts/mission_loop1.py",
          "success": true,
          "duration": 0.014286041259765625,
          "output": "FEATURE_ACTIVITY_MAP.md already exists, enhancing...\n\u2713 Loop 1 complete\n"
        },
        {
          "loop": "LOOP2",
          "script": "scripts/mission_loop2.py",
          "success": true,
          "duration": 0.014603614807128906,
          "output": "Generating ENV_BUG_DATA_AUDIT.md...\nGenerating DATA_CYCLE_MAP.md...\n\u2713 Loop 2 complete\n"
        },
        {
          "loop": "LOOP3",
          "script": "scripts/mission_loop3.py",
          "success": true,
          "duration": 0.009087085723876953,
          "output": "Generating ARCH_DECISIONS.md...\nGenerating ARCH_BLUEPRINT.md...\n\u2713 Loop 3 complete\n"
        },
        {
          "loop": "LOOP4",
          "script": "scripts/mission_loop4.py",
          "success": true,
          "duration": 0.00882863998413086,
          "output": "Enhancing FEATURE_ACTIVITY_MAP.md with routes...\nUpdating legacy_vs_current_diff.md...\n\u2713 Loop 4 complete\n"
        },
        {
          "loop": "LOOP5",
          "script": "scripts/mission_loop5.py",
          "success": true,
          "duration": 0.016249656677246094,
          "output": "Building IMPLEMENTATION_CHECKLIST.md...\n\u2713 Loop 5 complete - 324 items created\n"
        },
        {
          "loop": "LOOP6",
          "script": "scripts/mission_loop6.py",
          "success": true,
          "duration": 0.13946199417114258,
          "output": "Loading all reports and data...\nCalculating alignment delta...\nBuilding crosslinks...\nGenerating source of truth document...\nGenerating organizer manifest...\n\n\u2713 Source of Truth document created: docs/plan/OPENPOLICY_V2_SOURCE_OF_TRUTH.md\n\u2713 Organizer manifest created: reports/organizer_manifest.json\n\nAlignment Summary:\n  - architecture: 50.0%\n  - features: 0.0%\n  - data_flow: 80.6%\n  - routing: 1.3%\n  - quality: 100.0%\n  - operations: 0.0%\nRunning organizer and updating Source of Truth...\nRunning source_of_truth.py...\n\u2713 Loop 6 complete\n"
        }
      ],
      "enhancement_cycles": {
        "loop": "ENHANCE",
        "script": "scripts/mission_enhance.py",
        "success": true,
        "duration": 0.030576467514038086,
        "output": "\nRunning enhancement cycle 1/10...\n  \u2713 Cycle 1 complete - all 324 items enhanced\n\nRunning enhancement cycle 2/10...\n  \u2713 Cycle 2 complete - all 324 items enhanced\n\nRunning enhancement cycle 3/10...\n  \u2713 Cycle 3 complete - all 324 items enhanced\n\nRunning enhancement cycle 4/10...\n  \u2713 Cycle 4 complete - all 324 items enhanced\n\nRunning enhancement cycle 5/10...\n  \u2713 Cycle 5 complete - all 324 items enhanced\n\nRunning enhancement cycle 6/10...\n  \u2713 Cycle 6 complete - all 324 items enhanced\n\nRunning enhancement cycle 7/10...\n  \u2713 Cycle 7 complete - all 324 items enhanced\n\nRunning enhancement cycle 8/10...\n  \u2713 Cycle 8 complete - all 324 items enhanced\n\nRunning enhancement cycle 9/10...\n  \u2713 Cycle 9 complete - all 324 items enhanced\n\nRunning enhancement cycle 10/10...\n  \u2713 Cycle 10 complete - all 324 items enhanced\n\n\u2713 All 10 enhancement cycles complete!\n"
      },
      "end_time": "2025-08-23T19:13:28.015280",
      "duration": 0.2331855297088623,
      "success": true
    },
    {
      "pass_number": 3,
      "start_time": "2025-08-23T19:13:28.015683",
      "loops": [
        {
          "loop": "LOOP1",
          "script": "scripts/mission_loop1.py",
          "success": true,
          "duration": 0.014296531677246094,
          "output": "FEATURE_ACTIVITY_MAP.md already exists, enhancing...\n\u2713 Loop 1 complete\n"
        },
        {
          "loop": "LOOP2",
          "script": "scripts/mission_loop2.py",
          "success": true,
          "duration": 0.014549493789672852,
          "output": "Generating ENV_BUG_DATA_AUDIT.md...\nGenerating DATA_CYCLE_MAP.md...\n\u2713 Loop 2 complete\n"
        },
        {
          "loop": "LOOP3",
          "script": "scripts/mission_loop3.py",
          "success": true,
          "duration": 0.008782625198364258,
          "output": "Generating ARCH_DECISIONS.md...\nGenerating ARCH_BLUEPRINT.md...\n\u2713 Loop 3 complete\n"
        },
        {
          "loop": "LOOP4",
          "script": "scripts/mission_loop4.py",
          "success": true,
          "duration": 0.008692026138305664,
          "output": "Enhancing FEATURE_ACTIVITY_MAP.md with routes...\nUpdating legacy_vs_current_diff.md...\n\u2713 Loop 4 complete\n"
        },
        {
          "loop": "LOOP5",
          "script": "scripts/mission_loop5.py",
          "success": true,
          "duration": 0.01596999168395996,
          "output": "Building IMPLEMENTATION_CHECKLIST.md...\n\u2713 Loop 5 complete - 324 items created\n"
        },
        {
          "loop": "LOOP6",
          "script": "scripts/mission_loop6.py",
          "success": true,
          "duration": 0.13832473754882812,
          "output": "Loading all reports and data...\nCalculating alignment delta...\nBuilding crosslinks...\nGenerating source of truth document...\nGenerating organizer manifest...\n\n\u2713 Source of Truth document created: docs/plan/OPENPOLICY_V2_SOURCE_OF_TRUTH.md\n\u2713 Organizer manifest created: reports/organizer_manifest.json\n\nAlignment Summary:\n  - architecture: 50.0%\n  - features: 0.0%\n  - data_flow: 80.6%\n  - routing: 1.3%\n  - quality: 100.0%\n  - operations: 0.0%\nRunning organizer and updating Source of Truth...\nRunning source_of_truth.py...\n\u2713 Loop 6 complete\n"
        }
      ],
      "enhancement_cycles": {
        "loop": "ENHANCE",
        "script": "scripts/mission_enhance.py",
        "success": true,
        "duration": 0.03166985511779785,
        "output": "\nRunning enhancement cycle 1/10...\n  \u2713 Cycle 1 complete - all 324 items enhanced\n\nRunning enhancement cycle 2/10...\n  \u2713 Cycle 2 complete - all 324 items enhanced\n\nRunning enhancement cycle 3/10...\n  \u2713 Cycle 3 complete - all 324 items enhanced\n\nRunning enhancement cycle 4/10...\n  \u2713 Cycle 4 complete - all 324 items enhanced\n\nRunning enhancement cycle 5/10...\n  \u2713 Cycle 5 complete - all 324 items enhanced\n\nRunning enhancement cycle 6/10...\n  \u2713 Cycle 6 complete - all 324 items enhanced\n\nRunning enhancement cycle 7/10...\n  \u2713 Cycle 7 complete - all 324 items enhanced\n\nRunning enhancement cycle 8/10...\n  \u2713 Cycle 8 complete - all 324 items enhanced\n\nRunning enhancement cycle 9/10...\n  \u2713 Cycle 9 complete - all 324 items enhanced\n\nRunning enhancement cycle 10/10...\n  \u2713 Cycle 10 complete - all 324 items enhanced\n\n\u2713 All 10 enhancement cycles complete!\n"
      },
      "end_time": "2025-08-23T19:13:28.248046",
      "duration": 0.23237085342407227,
      "success": true
    },
    {
      "pass_number": 4,
      "start_time": "2025-08-23T19:13:28.248436",
      "loops": [
        {
          "loop": "LOOP1",
          "script": "scripts/mission_loop1.py",
          "success": true,
          "duration": 0.014060020446777344,
          "output": "FEATURE_ACTIVITY_MAP.md already exists, enhancing...\n\u2713 Loop 1 complete\n"
        },
        {
          "loop": "LOOP2",
          "script": "scripts/mission_loop2.py",
          "success": true,
          "duration": 0.014173507690429688,
          "output": "Generating ENV_BUG_DATA_AUDIT.md...\nGenerating DATA_CYCLE_MAP.md...\n\u2713 Loop 2 complete\n"
        },
        {
          "loop": "LOOP3",
          "script": "scripts/mission_loop3.py",
          "success": true,
          "duration": 0.009075641632080078,
          "output": "Generating ARCH_DECISIONS.md...\nGenerating ARCH_BLUEPRINT.md...\n\u2713 Loop 3 complete\n"
        },
        {
          "loop": "LOOP4",
          "script": "scripts/mission_loop4.py",
          "success": true,
          "duration": 0.008944511413574219,
          "output": "Enhancing FEATURE_ACTIVITY_MAP.md with routes...\nUpdating legacy_vs_current_diff.md...\n\u2713 Loop 4 complete\n"
        },
        {
          "loop": "LOOP5",
          "script": "scripts/mission_loop5.py",
          "success": true,
          "duration": 0.01599264144897461,
          "output": "Building IMPLEMENTATION_CHECKLIST.md...\n\u2713 Loop 5 complete - 324 items created\n"
        },
        {
          "loop": "LOOP6",
          "script": "scripts/mission_loop6.py",
          "success": true,
          "duration": 0.13632655143737793,
          "output": "Loading all reports and data...\nCalculating alignment delta...\nBuilding crosslinks...\nGenerating source of truth document...\nGenerating organizer manifest...\n\n\u2713 Source of Truth document created: docs/plan/OPENPOLICY_V2_SOURCE_OF_TRUTH.md\n\u2713 Organizer manifest created: reports/organizer_manifest.json\n\nAlignment Summary:\n  - architecture: 50.0%\n  - features: 0.0%\n  - data_flow: 80.6%\n  - routing: 1.3%\n  - quality: 100.0%\n  - operations: 0.0%\nRunning organizer and updating Source of Truth...\nRunning source_of_truth.py...\n\u2713 Loop 6 complete\n"
        }
      ],
      "enhancement_cycles": {
        "loop": "ENHANCE",
        "script": "scripts/mission_enhance.py",
        "success": true,
        "duration": 0.030745983123779297,
        "output": "\nRunning enhancement cycle 1/10...\n  \u2713 Cycle 1 complete - all 324 items enhanced\n\nRunning enhancement cycle 2/10...\n  \u2713 Cycle 2 complete - all 324 items enhanced\n\nRunning enhancement cycle 3/10...\n  \u2713 Cycle 3 complete - all 324 items enhanced\n\nRunning enhancement cycle 4/10...\n  \u2713 Cycle 4 complete - all 324 items enhanced\n\nRunning enhancement cycle 5/10...\n  \u2713 Cycle 5 complete - all 324 items enhanced\n\nRunning enhancement cycle 6/10...\n  \u2713 Cycle 6 complete - all 324 items enhanced\n\nRunning enhancement cycle 7/10...\n  \u2713 Cycle 7 complete - all 324 items enhanced\n\nRunning enhancement cycle 8/10...\n  \u2713 Cycle 8 complete - all 324 items enhanced\n\nRunning enhancement cycle 9/10...\n  \u2713 Cycle 9 complete - all 324 items enhanced\n\nRunning enhancement cycle 10/10...\n  \u2713 Cycle 10 complete - all 324 items enhanced\n\n\u2713 All 10 enhancement cycles complete!\n"
      },
      "end_time": "2025-08-23T19:13:28.477824",
      "duration": 0.22939491271972656,
      "success": true
    },
    {
      "pass_number": 5,
      "start_time": "2025-08-23T19:13:28.478259",
      "loops": [
        {
          "loop": "LOOP1",
          "script": "scripts/mission_loop1.py",
          "success": true,
          "duration": 0.014106273651123047,
          "output": "FEATURE_ACTIVITY_MAP.md already exists, enhancing...\n\u2713 Loop 1 complete\n"
        },
        {
          "loop": "LOOP2",
          "script": "scripts/mission_loop2.py",
          "success": true,
          "duration": 0.01437687873840332,
          "output": "Generating ENV_BUG_DATA_AUDIT.md...\nGenerating DATA_CYCLE_MAP.md...\n\u2713 Loop 2 complete\n"
        },
        {
          "loop": "LOOP3",
          "script": "scripts/mission_loop3.py",
          "success": true,
          "duration": 0.009285688400268555,
          "output": "Generating ARCH_DECISIONS.md...\nGenerating ARCH_BLUEPRINT.md...\n\u2713 Loop 3 complete\n"
        },
        {
          "loop": "LOOP4",
          "script": "scripts/mission_loop4.py",
          "success": true,
          "duration": 0.00892329216003418,
          "output": "Enhancing FEATURE_ACTIVITY_MAP.md with routes...\nUpdating legacy_vs_current_diff.md...\n\u2713 Loop 4 complete\n"
        },
        {
          "loop": "LOOP5",
          "script": "scripts/mission_loop5.py",
          "success": true,
          "duration": 0.01610541343688965,
          "output": "Building IMPLEMENTATION_CHECKLIST.md...\n\u2713 Loop 5 complete - 324 items created\n"
        },
        {
          "loop": "LOOP6",
          "script": "scripts/mission_loop6.py",
          "success": true,
          "duration": 0.13603591918945312,
          "output": "Loading all reports and data...\nCalculating alignment delta...\nBuilding crosslinks...\nGenerating source of truth document...\nGenerating organizer manifest...\n\n\u2713 Source of Truth document created: docs/plan/OPENPOLICY_V2_SOURCE_OF_TRUTH.md\n\u2713 Organizer manifest created: reports/organizer_manifest.json\n\nAlignment Summary:\n  - architecture: 50.0%\n  - features: 0.0%\n  - data_flow: 80.6%\n  - routing: 1.3%\n  - quality: 100.0%\n  - operations: 0.0%\nRunning organizer and updating Source of Truth...\nRunning source_of_truth.py...\n\u2713 Loop 6 complete\n"
        }
      ],
      "enhancement_cycles": {
        "loop": "ENHANCE",
        "script": "scripts/mission_enhance.py",
        "success": true,
        "duration": 0.02937173843383789,
        "output": "\nRunning enhancement cycle 1/10...\n  \u2713 Cycle 1 complete - all 324 items enhanced\n\nRunning enhancement cycle 2/10...\n  \u2713 Cycle 2 complete - all 324 items enhanced\n\nRunning enhancement cycle 3/10...\n  \u2713 Cycle 3 complete - all 324 items enhanced\n\nRunning enhancement cycle 4/10...\n  \u2713 Cycle 4 complete - all 324 items enhanced\n\nRunning enhancement cycle 5/10...\n  \u2713 Cycle 5 complete - all 324 items enhanced\n\nRunning enhancement cycle 6/10...\n  \u2713 Cycle 6 complete - all 324 items enhanced\n\nRunning enhancement cycle 7/10...\n  \u2713 Cycle 7 complete - all 324 items enhanced\n\nRunning enhancement cycle 8/10...\n  \u2713 Cycle 8 complete - all 324 items enhanced\n\nRunning enhancement cycle 9/10...\n  \u2713 Cycle 9 complete - all 324 items enhanced\n\nRunning enhancement cycle 10/10...\n  \u2713 Cycle 10 complete - all 324 items enhanced\n\n\u2713 All 10 enhancement cycles complete!\n"
      },
      "end_time": "2025-08-23T19:13:28.706542",
      "duration": 0.22828936576843262,
      "success": true
    },
    {
      "pass_number": 6,
      "start_time": "2025-08-23T19:13:28.706998",
      "loops": [
        {
          "loop": "LOOP1",
          "script": "scripts/mission_loop1.py",
          "success": true,
          "duration": 0.014093399047851562,
          "output": "FEATURE_ACTIVITY_MAP.md already exists, enhancing...\n\u2713 Loop 1 complete\n"
        },
        {
          "loop": "LOOP2",
          "script": "scripts/mission_loop2.py",
          "success": true,
          "duration": 0.01440739631652832,
          "output": "Generating ENV_BUG_DATA_AUDIT.md...\nGenerating DATA_CYCLE_MAP.md...\n\u2713 Loop 2 complete\n"
        },
        {
          "loop": "LOOP3",
          "script": "scripts/mission_loop3.py",
          "success": true,
          "duration": 0.008942842483520508,
          "output": "Generating ARCH_DECISIONS.md...\nGenerating ARCH_BLUEPRINT.md...\n\u2713 Loop 3 complete\n"
        },
        {
          "loop": "LOOP4",
          "script": "scripts/mission_loop4.py",
          "success": true,
          "duration": 0.009044408798217773,
          "output": "Enhancing FEATURE_ACTIVITY_MAP.md with routes...\nUpdating legacy_vs_current_diff.md...\n\u2713 Loop 4 complete\n"
        },
        {
          "loop": "LOOP5",
          "script": "scripts/mission_loop5.py",
          "success": true,
          "duration": 0.015911102294921875,
          "output": "Building IMPLEMENTATION_CHECKLIST.md...\n\u2713 Loop 5 complete - 324 items created\n"
        },
        {
          "loop": "LOOP6",
          "script": "scripts/mission_loop6.py",
          "success": true,
          "duration": 0.13847827911376953,
          "output": "Loading all reports and data...\nCalculating alignment delta...\nBuilding crosslinks...\nGenerating source of truth document...\nGenerating organizer manifest...\n\n\u2713 Source of Truth document created: docs/plan/OPENPOLICY_V2_SOURCE_OF_TRUTH.md\n\u2713 Organizer manifest created: reports/organizer_manifest.json\n\nAlignment Summary:\n  - architecture: 50.0%\n  - features: 0.0%\n  - data_flow: 80.6%\n  - routing: 1.3%\n  - quality: 100.0%\n  - operations: 0.0%\nRunning organizer and updating Source of Truth...\nRunning source_of_truth.py...\n\u2713 Loop 6 complete\n"
        }
      ],
      "enhancement_cycles": {
        "loop": "ENHANCE",
        "script": "scripts/mission_enhance.py",
        "success": true,
        "duration": 0.029857397079467773,
        "output": "\nRunning enhancement cycle 1/10...\n  \u2713 Cycle 1 complete - all 324 items enhanced\n\nRunning enhancement cycle 2/10...\n  \u2713 Cycle 2 complete - all 324 items enhanced\n\nRunning enhancement cycle 3/10...\n  \u2713 Cycle 3 complete - all 324 items enhanced\n\nRunning enhancement cycle 4/10...\n  \u2713 Cycle 4 complete - all 324 items enhanced\n\nRunning enhancement cycle 5/10...\n  \u2713 Cycle 5 complete - all 324 items enhanced\n\nRunning enhancement cycle 6/10...\n  \u2713 Cycle 6 complete - all 324 items enhanced\n\nRunning enhancement cycle 7/10...\n  \u2713 Cycle 7 complete - all 324 items enhanced\n\nRunning enhancement cycle 8/10...\n  \u2713 Cycle 8 complete - all 324 items enhanced\n\nRunning enhancement cycle 9/10...\n  \u2713 Cycle 9 complete - all 324 items enhanced\n\nRunning enhancement cycle 10/10...\n  \u2713 Cycle 10 complete - all 324 items enhanced\n\n\u2713 All 10 enhancement cycles complete!\n"
      },
      "end_time": "2025-08-23T19:13:28.937805",
      "duration": 0.23081231117248535,
      "success": true
    },
    {
      "pass_number": 7,
      "start_time": "2025-08-23T19:13:28.938335",
      "loops": [
        {
          "loop": "LOOP1",
          "script": "scripts/mission_loop1.py",
          "success": true,
          "duration": 0.014069080352783203,
          "output": "FEATURE_ACTIVITY_MAP.md already exists, enhancing...\n\u2713 Loop 1 complete\n"
        },
        {
          "loop": "LOOP2",
          "script": "scripts/mission_loop2.py",
          "success": true,
          "duration": 0.014601469039916992,
          "output": "Generating ENV_BUG_DATA_AUDIT.md...\nGenerating DATA_CYCLE_MAP.md...\n\u2713 Loop 2 complete\n"
        },
        {
          "loop": "LOOP3",
          "script": "scripts/mission_loop3.py",
          "success": true,
          "duration": 0.008908748626708984,
          "output": "Generating ARCH_DECISIONS.md...\nGenerating ARCH_BLUEPRINT.md...\n\u2713 Loop 3 complete\n"
        },
        {
          "loop": "LOOP4",
          "script": "scripts/mission_loop4.py",
          "success": true,
          "duration": 0.009036779403686523,
          "output": "Enhancing FEATURE_ACTIVITY_MAP.md with routes...\nUpdating legacy_vs_current_diff.md...\n\u2713 Loop 4 complete\n"
        },
        {
          "loop": "LOOP5",
          "script": "scripts/mission_loop5.py",
          "success": true,
          "duration": 0.01605844497680664,
          "output": "Building IMPLEMENTATION_CHECKLIST.md...\n\u2713 Loop 5 complete - 324 items created\n"
        },
        {
          "loop": "LOOP6",
          "script": "scripts/mission_loop6.py",
          "success": true,
          "duration": 0.13637995719909668,
          "output": "Loading all reports and data...\nCalculating alignment delta...\nBuilding crosslinks...\nGenerating source of truth document...\nGenerating organizer manifest...\n\n\u2713 Source of Truth document created: docs/plan/OPENPOLICY_V2_SOURCE_OF_TRUTH.md\n\u2713 Organizer manifest created: reports/organizer_manifest.json\n\nAlignment Summary:\n  - architecture: 50.0%\n  - features: 0.0%\n  - data_flow: 80.6%\n  - routing: 1.3%\n  - quality: 100.0%\n  - operations: 0.0%\nRunning organizer and updating Source of Truth...\nRunning source_of_truth.py...\n\u2713 Loop 6 complete\n"
        }
      ],
      "enhancement_cycles": {
        "loop": "ENHANCE",
        "script": "scripts/mission_enhance.py",
        "success": true,
        "duration": 0.031167030334472656,
        "output": "\nRunning enhancement cycle 1/10...\n  \u2713 Cycle 1 complete - all 324 items enhanced\n\nRunning enhancement cycle 2/10...\n  \u2713 Cycle 2 complete - all 324 items enhanced\n\nRunning enhancement cycle 3/10...\n  \u2713 Cycle 3 complete - all 324 items enhanced\n\nRunning enhancement cycle 4/10...\n  \u2713 Cycle 4 complete - all 324 items enhanced\n\nRunning enhancement cycle 5/10...\n  \u2713 Cycle 5 complete - all 324 items enhanced\n\nRunning enhancement cycle 6/10...\n  \u2713 Cycle 6 complete - all 324 items enhanced\n\nRunning enhancement cycle 7/10...\n  \u2713 Cycle 7 complete - all 324 items enhanced\n\nRunning enhancement cycle 8/10...\n  \u2713 Cycle 8 complete - all 324 items enhanced\n\nRunning enhancement cycle 9/10...\n  \u2713 Cycle 9 complete - all 324 items enhanced\n\nRunning enhancement cycle 10/10...\n  \u2713 Cycle 10 complete - all 324 items enhanced\n\n\u2713 All 10 enhancement cycles complete!\n"
      },
      "end_time": "2025-08-23T19:13:29.168628",
      "duration": 0.2302999496459961,
      "success": true
    },
    {
      "pass_number": 8,
      "start_time": "2025-08-23T19:13:29.169265",
      "loops": [
        {
          "loop": "LOOP1",
          "script": "scripts/mission_loop1.py",
          "success": true,
          "duration": 0.013918638229370117,
          "output": "FEATURE_ACTIVITY_MAP.md already exists, enhancing...\n\u2713 Loop 1 complete\n"
        },
        {
          "loop": "LOOP2",
          "script": "scripts/mission_loop2.py",
          "success": true,
          "duration": 0.014467477798461914,
          "output": "Generating ENV_BUG_DATA_AUDIT.md...\nGenerating DATA_CYCLE_MAP.md...\n\u2713 Loop 2 complete\n"
        },
        {
          "loop": "LOOP3",
          "script": "scripts/mission_loop3.py",
          "success": true,
          "duration": 0.00876617431640625,
          "output": "Generating ARCH_DECISIONS.md...\nGenerating ARCH_BLUEPRINT.md...\n\u2713 Loop 3 complete\n"
        },
        {
          "loop": "LOOP4",
          "script": "scripts/mission_loop4.py",
          "success": true,
          "duration": 0.008814811706542969,
          "output": "Enhancing FEATURE_ACTIVITY_MAP.md with routes...\nUpdating legacy_vs_current_diff.md...\n\u2713 Loop 4 complete\n"
        },
        {
          "loop": "LOOP5",
          "script": "scripts/mission_loop5.py",
          "success": true,
          "duration": 0.016000986099243164,
          "output": "Building IMPLEMENTATION_CHECKLIST.md...\n\u2713 Loop 5 complete - 324 items created\n"
        },
        {
          "loop": "LOOP6",
          "script": "scripts/mission_loop6.py",
          "success": true,
          "duration": 0.138289213180542,
          "output": "Loading all reports and data...\nCalculating alignment delta...\nBuilding crosslinks...\nGenerating source of truth document...\nGenerating organizer manifest...\n\n\u2713 Source of Truth document created: docs/plan/OPENPOLICY_V2_SOURCE_OF_TRUTH.md\n\u2713 Organizer manifest created: reports/organizer_manifest.json\n\nAlignment Summary:\n  - architecture: 50.0%\n  - features: 0.0%\n  - data_flow: 80.6%\n  - routing: 1.3%\n  - quality: 100.0%\n  - operations: 0.0%\nRunning organizer and updating Source of Truth...\nRunning source_of_truth.py...\n\u2713 Loop 6 complete\n"
        }
      ],
      "enhancement_cycles": {
        "loop": "ENHANCE",
        "script": "scripts/mission_enhance.py",
        "success": true,
        "duration": 0.030471086502075195,
        "output": "\nRunning enhancement cycle 1/10...\n  \u2713 Cycle 1 complete - all 324 items enhanced\n\nRunning enhancement cycle 2/10...\n  \u2713 Cycle 2 complete - all 324 items enhanced\n\nRunning enhancement cycle 3/10...\n  \u2713 Cycle 3 complete - all 324 items enhanced\n\nRunning enhancement cycle 4/10...\n  \u2713 Cycle 4 complete - all 324 items enhanced\n\nRunning enhancement cycle 5/10...\n  \u2713 Cycle 5 complete - all 324 items enhanced\n\nRunning enhancement cycle 6/10...\n  \u2713 Cycle 6 complete - all 324 items enhanced\n\nRunning enhancement cycle 7/10...\n  \u2713 Cycle 7 complete - all 324 items enhanced\n\nRunning enhancement cycle 8/10...\n  \u2713 Cycle 8 complete - all 324 items enhanced\n\nRunning enhancement cycle 9/10...\n  \u2713 Cycle 9 complete - all 324 items enhanced\n\nRunning enhancement cycle 10/10...\n  \u2713 Cycle 10 complete - all 324 items enhanced\n\n\u2713 All 10 enhancement cycles complete!\n"
      },
      "end_time": "2025-08-23T19:13:29.400060",
      "duration": 0.23080086708068848,
      "success": true
    },
    {
      "pass_number": 9,
      "start_time": "2025-08-23T19:13:29.400647",
      "loops": [
        {
          "loop": "LOOP1",
          "script": "scripts/mission_loop1.py",
          "success": true,
          "duration": 0.014356374740600586,
          "output": "FEATURE_ACTIVITY_MAP.md already exists, enhancing...\n\u2713 Loop 1 complete\n"
        },
        {
          "loop": "LOOP2",
          "script": "scripts/mission_loop2.py",
          "success": true,
          "duration": 0.014185428619384766,
          "output": "Generating ENV_BUG_DATA_AUDIT.md...\nGenerating DATA_CYCLE_MAP.md...\n\u2713 Loop 2 complete\n"
        },
        {
          "loop": "LOOP3",
          "script": "scripts/mission_loop3.py",
          "success": true,
          "duration": 0.008503437042236328,
          "output": "Generating ARCH_DECISIONS.md...\nGenerating ARCH_BLUEPRINT.md...\n\u2713 Loop 3 complete\n"
        },
        {
          "loop": "LOOP4",
          "script": "scripts/mission_loop4.py",
          "success": true,
          "duration": 0.009035348892211914,
          "output": "Enhancing FEATURE_ACTIVITY_MAP.md with routes...\nUpdating legacy_vs_current_diff.md...\n\u2713 Loop 4 complete\n"
        },
        {
          "loop": "LOOP5",
          "script": "scripts/mission_loop5.py",
          "success": true,
          "duration": 0.016123294830322266,
          "output": "Building IMPLEMENTATION_CHECKLIST.md...\n\u2713 Loop 5 complete - 324 items created\n"
        },
        {
          "loop": "LOOP6",
          "script": "scripts/mission_loop6.py",
          "success": true,
          "duration": 0.13879656791687012,
          "output": "Loading all reports and data...\nCalculating alignment delta...\nBuilding crosslinks...\nGenerating source of truth document...\nGenerating organizer manifest...\n\n\u2713 Source of Truth document created: docs/plan/OPENPOLICY_V2_SOURCE_OF_TRUTH.md\n\u2713 Organizer manifest created: reports/organizer_manifest.json\n\nAlignment Summary:\n  - architecture: 50.0%\n  - features: 0.0%\n  - data_flow: 80.6%\n  - routing: 1.3%\n  - quality: 100.0%\n  - operations: 0.0%\nRunning organizer and updating Source of Truth...\nRunning source_of_truth.py...\n\u2713 Loop 6 complete\n"
        }
      ],
      "enhancement_cycles": {
        "loop": "ENHANCE",
        "script": "scripts/mission_enhance.py",
        "success": true,
        "duration": 0.030454635620117188,
        "output": "\nRunning enhancement cycle 1/10...\n  \u2713 Cycle 1 complete - all 324 items enhanced\n\nRunning enhancement cycle 2/10...\n  \u2713 Cycle 2 complete - all 324 items enhanced\n\nRunning enhancement cycle 3/10...\n  \u2713 Cycle 3 complete - all 324 items enhanced\n\nRunning enhancement cycle 4/10...\n  \u2713 Cycle 4 complete - all 324 items enhanced\n\nRunning enhancement cycle 5/10...\n  \u2713 Cycle 5 complete - all 324 items enhanced\n\nRunning enhancement cycle 6/10...\n  \u2713 Cycle 6 complete - all 324 items enhanced\n\nRunning enhancement cycle 7/10...\n  \u2713 Cycle 7 complete - all 324 items enhanced\n\nRunning enhancement cycle 8/10...\n  \u2713 Cycle 8 complete - all 324 items enhanced\n\nRunning enhancement cycle 9/10...\n  \u2713 Cycle 9 complete - all 324 items enhanced\n\nRunning enhancement cycle 10/10...\n  \u2713 Cycle 10 complete - all 324 items enhanced\n\n\u2713 All 10 enhancement cycles complete!\n"
      },
      "end_time": "2025-08-23T19:13:29.632170",
      "duration": 0.23153090476989746,
      "success": true
    },
    {
      "pass_number": 10,
      "start_time": "2025-08-23T19:13:29.632793",
      "loops": [
        {
          "loop": "LOOP1",
          "script": "scripts/mission_loop1.py",
          "success": true,
          "duration": 0.014253854751586914,
          "output": "FEATURE_ACTIVITY_MAP.md already exists, enhancing...\n\u2713 Loop 1 complete\n"
        },
        {
          "loop": "LOOP2",
          "script": "scripts/mission_loop2.py",
          "success": true,
          "duration": 0.014633893966674805,
          "output": "Generating ENV_BUG_DATA_AUDIT.md...\nGenerating DATA_CYCLE_MAP.md...\n\u2713 Loop 2 complete\n"
        },
        {
          "loop": "LOOP3",
          "script": "scripts/mission_loop3.py",
          "success": true,
          "duration": 0.009072065353393555,
          "output": "Generating ARCH_DECISIONS.md...\nGenerating ARCH_BLUEPRINT.md...\n\u2713 Loop 3 complete\n"
        },
        {
          "loop": "LOOP4",
          "script": "scripts/mission_loop4.py",
          "success": true,
          "duration": 0.008959531784057617,
          "output": "Enhancing FEATURE_ACTIVITY_MAP.md with routes...\nUpdating legacy_vs_current_diff.md...\n\u2713 Loop 4 complete\n"
        },
        {
          "loop": "LOOP5",
          "script": "scripts/mission_loop5.py",
          "success": true,
          "duration": 0.01608109474182129,
          "output": "Building IMPLEMENTATION_CHECKLIST.md...\n\u2713 Loop 5 complete - 324 items created\n"
        },
        {
          "loop": "LOOP6",
          "script": "scripts/mission_loop6.py",
          "success": true,
          "duration": 0.13720107078552246,
          "output": "Loading all reports and data...\nCalculating alignment delta...\nBuilding crosslinks...\nGenerating source of truth document...\nGenerating organizer manifest...\n\n\u2713 Source of Truth document created: docs/plan/OPENPOLICY_V2_SOURCE_OF_TRUTH.md\n\u2713 Organizer manifest created: reports/organizer_manifest.json\n\nAlignment Summary:\n  - architecture: 50.0%\n  - features: 0.0%\n  - data_flow: 80.6%\n  - routing: 1.3%\n  - quality: 100.0%\n  - operations: 0.0%\nRunning organizer and updating Source of Truth...\nRunning source_of_truth.py...\n\u2713 Loop 6 complete\n"
        }
      ],
      "enhancement_cycles": {
        "loop": "ENHANCE",
        "script": "scripts/mission_enhance.py",
        "success": true,
        "duration": 0.03136587142944336,
        "output": "\nRunning enhancement cycle 1/10...\n  \u2713 Cycle 1 complete - all 324 items enhanced\n\nRunning enhancement cycle 2/10...\n  \u2713 Cycle 2 complete - all 324 items enhanced\n\nRunning enhancement cycle 3/10...\n  \u2713 Cycle 3 complete - all 324 items enhanced\n\nRunning enhancement cycle 4/10...\n  \u2713 Cycle 4 complete - all 324 items enhanced\n\nRunning enhancement cycle 5/10...\n  \u2713 Cycle 5 complete - all 324 items enhanced\n\nRunning enhancement cycle 6/10...\n  \u2713 Cycle 6 complete - all 324 items enhanced\n\nRunning enhancement cycle 7/10...\n  \u2713 Cycle 7 complete - all 324 items enhanced\n\nRunning enhancement cycle 8/10...\n  \u2713 Cycle 8 complete - all 324 items enhanced\n\nRunning enhancement cycle 9/10...\n  \u2713 Cycle 9 complete - all 324 items enhanced\n\nRunning enhancement cycle 10/10...\n  \u2713 Cycle 10 complete - all 324 items enhanced\n\n\u2713 All 10 enhancement cycles complete!\n"
      },
      "end_time": "2025-08-23T19:13:29.864427",
      "duration": 0.2316420078277588,
      "success": true
    }
  ],
  "started_at": "2025-08-23T19:13:27.528051",
  "status": "completed",
  "completed_at": "2025-08-23T19:13:29.865155"
}